l4v1/__init__.py
l4v1/price_volume_mix.py
l4v1-0.2.1.dist-info/METADATA
l4v1-0.2.1.dist-info/WHEEL
l4v1-0.2.1.dist-info/licenses/LICENSE
l4v1-0.2.1.dist-info/RECORD
