Metadata-Version: 2.3
Name: l4v1
Version: 0.2.1
Summary: A Python library to simplify data-analytics tasks
Author-email: Miro Lavi <info.l4v1@gmail.com>
License-File: LICENSE
Requires-Python: >=3.10
Requires-Dist: plotly>=5.20.0
Requires-Dist: polars>=0.20.23
Requires-Dist: xlsxwriter>=3.2.0
